vad/__init__.py
vad/energy_vad.py
vad-1.0.2.dist-info/LICENSE
vad-1.0.2.dist-info/METADATA
vad-1.0.2.dist-info/WHEEL
vad-1.0.2.dist-info/top_level.txt
vad-1.0.2.dist-info/RECORD
