Metadata-Version: 2.1
Name: vad
Version: 1.0.2
Summary: VAD - Simple Voice Activity Detection
Home-page: https://github.com/MorenoLaQuatra/vad
Author: Moreno La Quatra
Author-email: moreno.laquatra@gmail.com
Classifier: Programming Language :: Python :: 3
Classifier: Operating System :: OS Independent
Classifier: License :: OSI Approved :: GNU General Public License v3 (GPLv3)
License-File: LICENSE
